dirgh/__init__.py
dirgh/cli.py
dirgh/cli_helper.py
dirgh/download.py
dirgh/main.py
dirgh-0.3.1.dist-info/WHEEL
dirgh-0.3.1.dist-info/METADATA
dirgh-0.3.1.dist-info/entry_points.txt
dirgh-0.3.1.dist-info/RECORD
