Metadata-Version: 2.1
Name: dirgh
Version: 0.3.1
Summary: With dirgh you can easily download a directory from GitHub programmatically from Python or using the CLI.
License: Apache-2.0
Author: tiptenbrink
Author-email: 75669206+tiptenbrink@users.noreply.github.com
Requires-Python: >=3.9,<4.0
Classifier: License :: OSI Approved :: Apache Software License
Classifier: Programming Language :: Python :: 3
Classifier: Programming Language :: Python :: 3.9
Classifier: Programming Language :: Python :: 3.10
Classifier: Programming Language :: Python :: 3.11
Requires-Dist: httpx (>=0.23.0,<0.26.0)
Requires-Dist: trio (>=0.20.0,<0.23.0)
